starlette_aws_lambda_api_client/__init__.py
starlette_aws_lambda_api_client/_json.py
starlette_aws_lambda_api_client/_lambda.py
starlette_aws_lambda_api_client/_session.py
starlette_aws_lambda_api_client/py.typed
starlette_aws_lambda_api_client-0.1.0.dist-info/LICENSE
starlette_aws_lambda_api_client-0.1.0.dist-info/WHEEL
starlette_aws_lambda_api_client-0.1.0.dist-info/METADATA
starlette_aws_lambda_api_client-0.1.0.dist-info/RECORD
