Metadata-Version: 2.1
Name: starlette-aws-lambda-api-client
Version: 0.1.0
Summary: aio_lambda_api with AWS lambda backend client for Starlette/FastAPI
Home-page: https://github.com/JGoutin/starlette_aws_lambda_api_client
License: BSD-2-Clause
Keywords: starlette,fastapi,aws
Author: JGoutin
Requires-Python: >=3.8,<4.0
Classifier: Development Status :: 4 - Beta
Classifier: Framework :: FastAPI
Classifier: Intended Audience :: Developers
Classifier: License :: OSI Approved :: BSD License
Classifier: Programming Language :: Python :: 3
Classifier: Programming Language :: Python :: 3.8
Classifier: Programming Language :: Python :: 3.9
Classifier: Programming Language :: Python :: 3.10
Classifier: Programming Language :: Python :: 3.11
Classifier: Typing :: Typed
Provides-Extra: speedups
Requires-Dist: aioboto3
Requires-Dist: aiohttp[speedups] (>3.8) ; extra == "speedups"
Requires-Dist: jhalog
Requires-Dist: orjson ; extra == "speedups"
Requires-Dist: starlette
Project-URL: Repository, https://github.com/JGoutin/starlette_aws_lambda_api_client
